js.jquery-3.6.1-py3.8-nspkg.pth
js/jquery/__init__.py
js/jquery/test_jquery.rst
js/jquery/resources/jquery-3.6.1.js
js/jquery/resources/jquery-3.6.1.min.js
js/jquery/resources/jquery-3.6.1.min.map
js/jquery/resources/jquery-3.6.1.slim.js
js/jquery/resources/jquery-3.6.1.slim.min.js
js/jquery/resources/jquery-3.6.1.slim.min.map
js.jquery-3.6.1.dist-info/LICENSE.txt
js.jquery-3.6.1.dist-info/METADATA
js.jquery-3.6.1.dist-info/WHEEL
js.jquery-3.6.1.dist-info/entry_points.txt
js.jquery-3.6.1.dist-info/namespace_packages.txt
js.jquery-3.6.1.dist-info/top_level.txt
js.jquery-3.6.1.dist-info/RECORD
