Metadata-Version: 2.1
Name: js.jquery
Version: 3.6.1
Summary: jQuery packaged for Fanstatic.
Home-page: https://bitbucket.org/fanstatic/js.jquery
Author: Fanstatic Developers
Author-email: fanstatic@googlegroups.com
License: BSD
Keywords: fanstatic jQuery WSGI middleware static asset
Platform: UNKNOWN
Classifier: Development Status :: 6 - Mature
Classifier: Environment :: Web Environment
Classifier: Intended Audience :: Developers
Classifier: License :: OSI Approved :: BSD License
Classifier: Natural Language :: English
Classifier: Operating System :: OS Independent
Classifier: Programming Language :: Python :: 2
Classifier: Programming Language :: Python :: 2.7
Classifier: Programming Language :: Python :: 3
Classifier: Programming Language :: Python :: 3.4
Classifier: Programming Language :: Python :: 3.5
Classifier: Programming Language :: Python :: 3.6
Classifier: Programming Language :: Python :: 3.7
Classifier: Topic :: Internet :: WWW/HTTP :: WSGI
Classifier: Topic :: Software Development :: Libraries :: Application Frameworks
Requires-Dist: fanstatic
Requires-Dist: setuptools
